{"animals":["SHEEP","WOLF"],"coordinates":[{"x":7.0,"y":9.0},{"x":15.0,"y":9.0}],"hunterStartPosition":{"x":15.0,"y":3.0},"hunterStartingInventory":{"REGULAR_TRAP":[{"TRAP_FILE":"assets/REGULAR_TRAP.png","inInventory":true,"onMap":false,"isSelected":false,"pos":{"x":0.0,"y":0.0},"xPos":0.0,"yPos":0.0,"type":"REGULAR_TRAP"},{"TRAP_FILE":"assets/REGULAR_TRAP.png","inInventory":true,"onMap":false,"isSelected":false,"pos":{"x":0.0,"y":0.0},"xPos":0.0,"yPos":0.0,"type":"REGULAR_TRAP"}],"WOLF_TRAP":[{"TRAP_FILE":"assets/WOLF_TRAP.png","inInventory":true,"onMap":false,"isSelected":false,"pos":{"x":0.0,"y":0.0},"xPos":0.0,"yPos":0.0,"type":"WOLF_TRAP"},{"TRAP_FILE":"assets/WOLF_TRAP.png","inInventory":true,"onMap":false,"isSelected":false,"pos":{"x":0.0,"y":0.0},"xPos":0.0,"yPos":0.0,"type":"WOLF_TRAP"}],"SHEEP_TRAP":[{"TRAP_FILE":"assets/SHEEP_TRAP.png","inInventory":true,"onMap":false,"isSelected":false,"pos":{"x":0.0,"y":0.0},"xPos":0.0,"yPos":0.0,"type":"SHEEP_TRAP"},{"TRAP_FILE":"assets/SHEEP_TRAP.png","inInventory":true,"onMap":false,"isSelected":false,"pos":{"x":0.0,"y":0.0},"xPos":0.0,"yPos":0.0,"type":"SHEEP_TRAP"}]},"layout":[["TREE","TREE","TREE","TREE","TREE","TREE","TREE","TREE","TREE","TREE","TREE","TREE","TREE","TREE","TREE","TREE","TREE","TREE","TREE","TREE","TREE","TREE","TREE","TREE","TREE","TREE","TREE","TREE","TREE","TREE","TREE","TREE"],["TREE","GRASS","GRASS","GRASS","GRASS","GRASS","GRASS","GRASS","GRASS","GRASS","GRASS","GRASS","GRASS","GRASS","GRASS","GRASS","GRASS","GRASS","GRASS","GRASS","GRASS","GRASS","GRASS","GRASS","GRASS","GRASS","GRASS","GRASS","GRASS","GRASS","GRASS","TREE"],["TREE","GRASS","BUSH","GRASS","BUSH","GRASS","GRASS","GRASS","BUSH","GRASS","GRASS","GRASS","GRASS","GRASS","GRASS","GRASS","GRASS","GRASS","GRASS","GRASS","GRASS","GRASS","GRASS","GRASS","GRASS","GRASS","GRASS","GRASS","GRASS","GRASS","GRASS","TREE"],["TREE","GRASS","BUSH","GRASS","BUSH","GRASS","GRASS","GRASS","BUSH","GRASS","GRASS","GRASS","GRASS","GRASS","GRASS","GRASS","GRASS","GRASS","GRASS","GRASS","GRASS","GRASS","GRASS","GRASS","GRASS","GRASS","GRASS","GRASS","GRASS","GRASS","GRASS","TREE"],["TREE","GRASS","BUSH","BUSH","BUSH","GRASS","GRASS","GRASS","BUSH","GRASS","GRASS","GRASS","GRASS","GRASS","GRASS","GRASS","GRASS","GRASS","GRASS","GRASS","GRASS","GRASS","GRASS","GRASS","GRASS","GRASS","GRASS","GRASS","GRASS","GRASS","GRASS","TREE"],["TREE","GRASS","BUSH","GRASS","BUSH","GRASS","GRASS","GRASS","GRASS","GRASS","GRASS","GRASS","GRASS","GRASS","GRASS","GRASS","GRASS","GRASS","GRASS","GRASS","GRASS","GRASS","GRASS","GRASS","GRASS","GRASS","GRASS","GRASS","GRASS","GRASS","GRASS","TREE"],["TREE","GRASS","BUSH","GRASS","BUSH","GRASS","GRASS","GRASS","BUSH","GRASS","GRASS","GRASS","GRASS","GRASS","GRASS","GRASS","GRASS","GRASS","GRASS","GRASS","GRASS","GRASS","GRASS","GRASS","GRASS","GRASS","GRASS","GRASS","GRASS","GRASS","GRASS","TREE"],["TREE","GRASS","GRASS","GRASS","GRASS","GRASS","GRASS","GRASS","GRASS","GRASS","GRASS","GRASS","GRASS","GRASS","GRASS","GRASS","GRASS","GRASS","GRASS","GRASS","GRASS","GRASS","GRASS","GRASS","GRASS","GRASS","GRASS","GRASS","GRASS","GRASS","GRASS","TREE"],["TREE","GRASS","GRASS","GRASS","GRASS","GRASS","GRASS","GRASS","GRASS","GRASS","GRASS","GRASS","GRASS","GRASS","GRASS","GRASS","GRASS","GRASS","GRASS","GRASS","GRASS","GRASS","GRASS","GRASS","GRASS","GRASS","GRASS","GRASS","GRASS","GRASS","GRASS","TREE"],["TREE","GRASS","GRASS","GRASS","GRASS","GRASS","GRASS","GRASS","GRASS","GRASS","GRASS","GRASS","GRASS","GRASS","GRASS","GRASS","GRASS","GRASS","GRASS","GRASS","GRASS","GRASS","GRASS","GRASS","GRASS","GRASS","GRASS","GRASS","GRASS","GRASS","GRASS","TREE"],["TREE","GRASS","GRASS","GRASS","GRASS","GRASS","GRASS","GRASS","GRASS","GRASS","GRASS","GRASS","GRASS","GRASS","GRASS","GRASS","GRASS","GRASS","GRASS","GRASS","GRASS","GRASS","GRASS","GRASS","GRASS","GRASS","GRASS","GRASS","GRASS","GRASS","GRASS","TREE"],["TREE","GRASS","GRASS","GRASS","GRASS","GRASS","GRASS","GRASS","GRASS","GRASS","GRASS","GRASS","GRASS","GRASS","GRASS","GRASS","GRASS","GRASS","GRASS","GRASS","GRASS","GRASS","GRASS","GRASS","GRASS","GRASS","GRASS","GRASS","GRASS","GRASS","GRASS","TREE"],["TREE","GRASS","GRASS","GRASS","GRASS","GRASS","GRASS","GRASS","GRASS","GRASS","GRASS","GRASS","GRASS","GRASS","GRASS","GRASS","GRASS","GRASS","GRASS","GRASS","GRASS","GRASS","GRASS","GRASS","GRASS","GRASS","GRASS","GRASS","GRASS","GRASS","GRASS","TREE"],["TREE","GRASS","GRASS","GRASS","GRASS","GRASS","GRASS","GRASS","GRASS","GRASS","GRASS","GRASS","GRASS","GRASS","GRASS","GRASS","GRASS","GRASS","GRASS","GRASS","GRASS","GRASS","GRASS","GRASS","GRASS","GRASS","GRASS","GRASS","GRASS","GRASS","GRASS","TREE"],["TREE","GRASS","GRASS","GRASS","GRASS","GRASS","GRASS","GRASS","GRASS","GRASS","GRASS","GRASS","GRASS","GRASS","GRASS","GRASS","GRASS","GRASS","GRASS","GRASS","GRASS","GRASS","GRASS","GRASS","GRASS","GRASS","GRASS","GRASS","GRASS","GRASS","GRASS","TREE"],["TREE","TREE","TREE","TREE","TREE","TREE","TREE","TREE","TREE","TREE","TREE","TREE","TREE","TREE","TREE","TREE","TREE","TREE","TREE","TREE","TREE","TREE","TREE","TREE","TREE","TREE","TREE","TREE","TREE","TREE","TREE","TREE"]]}